NormalDistribution/Distributions.py
NormalDistribution/Guassian.py
NormalDistribution/__init__.py
NormalDistribution-0.0.1.dist-info/LICENSE.txt
NormalDistribution-0.0.1.dist-info/METADATA
NormalDistribution-0.0.1.dist-info/WHEEL
NormalDistribution-0.0.1.dist-info/top_level.txt
NormalDistribution-0.0.1.dist-info/RECORD
