Metadata-Version: 2.1
Name: NormalDistribution
Version: 0.0.1
Summary: Normal (Gussian) Distributions
Home-page: https://github.com/aojewola/Package_NormalDistribution
Author: Ashim Ojewola
Author-email: asimiakin11@gmail.com
License: UNKNOWN
Platform: UNKNOWN
Classifier: Programming Language :: Python :: 3
Classifier: License :: OSI Approved :: MIT License
Classifier: Operating System :: OS Independent
Requires-Python: >=3.6
